pyflowapi/__init__.py
pyflowapi/server.py
pyflowapi-0.2.0.data/scripts/pyflowapi-server.py
pyflowapi-0.2.0.dist-info/licenses/LICENSE
pyflowapi-0.2.0.dist-info/METADATA
pyflowapi-0.2.0.dist-info/WHEEL
pyflowapi-0.2.0.dist-info/top_level.txt
pyflowapi-0.2.0.dist-info/RECORD
