Metadata-Version: 2.4
Name: pyflowapi
Version: 0.2.0
Summary: Async service toolchain
Home-page: https://github.com/senatoreg/pyflowapi
Author: Giovanni Senatore
Author-email: 
License: AGPL-3.0-or-later
Classifier: Programming Language :: Python :: 3
Classifier: License :: OSI Approved :: GNU Affero General Public License v3 or later (AGPLv3+)
Classifier: Operating System :: OS Independent
Requires-Python: >=3.8
License-File: LICENSE
Requires-Dist: fastapi>=0.115.11
Requires-Dist: uvicorn>=0.32.0
Requires-Dist: uvloop>=0.21.0
Requires-Dist: pyfreeflow>=0.2.0
Dynamic: author
Dynamic: classifier
Dynamic: description
Dynamic: description-content-type
Dynamic: home-page
Dynamic: license
Dynamic: license-file
Dynamic: requires-dist
Dynamic: requires-python
Dynamic: summary
